tarp/__init__.py
tarp/drp.py
tarp-0.1.1.dist-info/LICENSE
tarp-0.1.1.dist-info/METADATA
tarp-0.1.1.dist-info/WHEEL
tarp-0.1.1.dist-info/top_level.txt
tarp-0.1.1.dist-info/RECORD
