Metadata-Version: 2.1
Name: tarp
Version: 0.1.1
Summary: Statistical coverage testing in python.
Author-email: Adam Coogan <dr.adam.coogan@gmail.com>, Pablo Lemos <plemos91@gmail.com>
License: MIT License
Project-URL: homepage, https://github.com/Ciela-Institute/tarp
Project-URL: repository, https://github.com/Ciela-Institute/tarp
Project-URL: documentation, https://tarp.readthedocs.io/en/latest/
Keywords: bayesian,coverage,posterior,statistics
Classifier: Programming Language :: Python :: 3
Classifier: License :: OSI Approved :: MIT License
Classifier: Operating System :: OS Independent
Requires-Python: >=3.7
License-File: LICENSE
Requires-Dist: numpy
Provides-Extra: dev
Requires-Dist: build ; extra == 'dev'
Requires-Dist: furo ; extra == 'dev'
Requires-Dist: myst-parser ; extra == 'dev'
Requires-Dist: pip ; extra == 'dev'
Requires-Dist: pytest ; extra == 'dev'
Requires-Dist: sphinx ; extra == 'dev'
Requires-Dist: sphinx-autodoc-typehints ; extra == 'dev'
Requires-Dist: sphinx-pyproject ; extra == 'dev'
Requires-Dist: twine ; extra == 'dev'
